cdk_watchful/__init__.py
cdk_watchful/py.typed
cdk_watchful/_jsii/__init__.py
cdk_watchful/_jsii/cdk-watchful@0.6.458.jsii.tgz
cdk_watchful-0.6.458.dist-info/LICENSE
cdk_watchful-0.6.458.dist-info/METADATA
cdk_watchful-0.6.458.dist-info/WHEEL
cdk_watchful-0.6.458.dist-info/top_level.txt
cdk_watchful-0.6.458.dist-info/RECORD
