Metadata-Version: 2.1
Name: cdk-watchful
Version: 0.6.458
Summary: Watching your CDK apps since 2019
Home-page: https://github.com/eladb/cdk-watchful.git
Author: Amazon Web Services<aws-cdk-dev@amazon.com>
License: Apache-2.0
Project-URL: Source, https://github.com/eladb/cdk-watchful.git
Classifier: Intended Audience :: Developers
Classifier: Operating System :: OS Independent
Classifier: Programming Language :: JavaScript
Classifier: Programming Language :: Python :: 3 :: Only
Classifier: Programming Language :: Python :: 3.7
Classifier: Programming Language :: Python :: 3.8
Classifier: Programming Language :: Python :: 3.9
Classifier: Programming Language :: Python :: 3.10
Classifier: Programming Language :: Python :: 3.11
Classifier: Typing :: Typed
Classifier: Development Status :: 4 - Beta
Classifier: License :: OSI Approved
Requires-Python: ~=3.7
License-File: LICENSE
Requires-Dist: aws-cdk-lib <3.0.0,>=2.0.0
Requires-Dist: constructs <11.0.0,>=10.0.5
Requires-Dist: jsii <2.0.0,>=1.88.0
Requires-Dist: publication >=0.0.3
Requires-Dist: typeguard ~=2.13.3
